insightface/__init__.py
insightface/app/__init__.py
insightface/app/common.py
insightface/app/face_analysis.py
insightface/app/face_onnx_handler.py
insightface/model_zoo/__init__.py
insightface/model_zoo/arcface_onnx.py
insightface/model_zoo/face_detection.py
insightface/model_zoo/face_genderage.py
insightface/model_zoo/face_recognition.py
insightface/model_zoo/model_store.py
insightface/model_zoo/model_zoo.py
insightface/model_zoo/scrfd.py
insightface/utils/__init__.py
insightface/utils/common.py
insightface/utils/download.py
insightface/utils/face_align.py
insightface/utils/filesystem.py
insightface-0.2.1.dist-info/METADATA
insightface-0.2.1.dist-info/RECORD
insightface-0.2.1.dist-info/WHEEL
insightface-0.2.1.dist-info/top_level.txt
insightface-0.2.1.dist-info/zip-safe
