Metadata-Version: 1.0
Name: insightface
Version: 0.2.1
Summary: InsightFace Toolkit
Home-page: https://github.com/deepinsight/insightface
Author: InsightFace Contributors
Author-email: contact@insightface.ai
License: Apache-2.0
Platform: UNKNOWN
